Workbook

Sheet A_Inattention
A2: INATTENTION
B3: 0 = Jamais | 1 = Parfois | 2 = Souvent | 3 = Très souvent | C3: Evaluation 1 | D3: Evaluation 2
A4: Item | B4: Énoncé | C4: Valeur (0–3) | D4: Valeur (0-3)
A5: A1 | B5: Fait des erreurs d’inattention dans les travaux longs ou complexes (contrôles, devoirs, projets).
A6: A2 | B6: A de la difficulté à maintenir son attention sur une tâche scolaire.
A7: A3 | B7: Semble ne pas écouter quand on lui parle directement.
A8: A4 | B8: Ne termine pas ses travaux ou devoirs malgré des capacités suffisantes.
A9: A5 | B9: A des difficultés à planifier, organiser ou répartir son travail.
A10: A6 | B10: A de la difficulté à commencer une tâche (devoirs, travail, révisions), ce qui le/la met souvent en décalage.
A11: A7 | B11: Perd fréquemment le matériel nécessaire au travail scolaire malgré les stratégies mises en place pour l’aider.
A12: A8 | B12: Se laisse facilement distraire par l’environnement ou le numérique.
A13: A9 | B13: Oublie des devoirs, échéances ou consignes.
A14: A10 | B14: Évite ou repousse les tâches demandant un effort mental soutenu.
B16: Total catégorie | C16: =SUM(C5:C14) -> 0 | D16: =SUM(D5:D14) -> 0

Sheet B_HyperImpuls
A1: HYPERACTIVITE-IMPULSIVITE
B2: 0 = Jamais | 1 = Parfois | 2 = Souvent | 3 = Très souvent | C2: Evaluation 1 | D2: Evaluation 2
A3: Item | B3: Énoncé | C3: Valeur (0–3) | D3: Valeur (0-3)
A4: B11 | B4: Bouge souvent les mains, les pieds ou se balance sur sa chaise.
A5: B12 | B5: A du mal à rester assis longtemps.
A6: B13 | B6: Se lève ou se déplace à des moments inappropriés.
A7: B14 | B7: Ressent une agitation intérieure ou une impatience constante.
A8: B15 | B8: Parle excessivement ou dans des situations inappropriées.
A9: B16 | B9: Répond avant la fin des questions.
A10: B17 | B10: A du mal à attendre son tour.
A11: B18 | B11: Interrompt souvent les autres.
B13: Total catégorie | C13: =SUM(C4:C11) -> 0 | D13: =SUM(D4:D11) -> 0

Sheet C_Devoirs
A1: DEVOIRS
B2: 0 = Jamais | 1 = Parfois | 2 = Souvent | 3 = Très souvent | C2: Evaluation 1 | D2: Evaluation 2
A3: Item | B3: Énoncé | C3: Valeur (0–3) | D3: Valeur (0-3)
A4: C19 | B4: Met beaucoup de temps à commencer ses devoirs sans aide.
A5: C20 | B5: A besoin d’une présence constante pour rester au travail.
A6: C21 | B6: Les devoirs provoquent des tensions ou conflits à la maison.
A7: C22 | B7: Se décourage rapidement face aux devoirs longs ou difficiles.
A8: C23 | B8: Oublie ou ne rend pas des devoirs pourtant faits.
A9: C24 | B9: Travaille de manière très irrégulière (proportionnellement à l'intérêt).
A10: C25 | B10: A du mal à gérer le temps nécessaire aux devoirs.
A11: C26 | B11: Procrastine presque systématiquement.
A12: C27 | B12: Se fatigue mentalement très vite pendant les devoirs.
B14: Total catégorie | C14: =SUM(C4:C12) -> 0 | D14: =SUM(D4:D12) -> 0

Sheet D_Réactions_confrontation
A1: Réactions de confrontation (contexte scolaire)
B2: 0 = Jamais | 1 = Parfois | 2 = Souvent | 3 = Très souvent | C2: Evaluation 1 | D2: Evaluation 2
A3: Item | B3: Énoncé | C3: Valeur (0–3) | D3: Valeur (0-3)
A4: RC1 | B4: Refuse ou conteste une consigne lorsqu’elle est perçue comme trop difficile.
A5: RC2 | B5: Réagit avec colère, opposition ou provocation après un échec ou une remarque.
A6: RC3 | B6: Entre en négociation excessive ou en marchandage pour éviter une tâche.
A7: RC4 | B7: Adopte une attitude de défi ou de confrontation envers l’adulte.
A8: RC5 | B8: Se désengage volontairement de la tâche (silence, immobilité, refus d’écrire ou de parler).
A9: RC6 | B9: Attribue la responsabilité de la situation à l’adulte ou au cadre scolaire.
A10: RC7 | B10: Refuse ou rejette l’aide proposée lorsqu’une tâche devient difficile.
A11: RC8 | B11: A des difficultés à se calmer après un conflit ou une montée émotionnelle.
A12: RC9 | B12: A des difficultés à reprendre une tâche après une pause ou un temps de régulation.
A13: RC10 | B13: A des difficultés à réparer la relation après un conflit (excuses, reprise du lien).
B15: Total – Réactions de confrontation | C15: =SUM(C4:C13) -> 0 | D15: =SUM(D4:D13) -> 0

Sheet E_Impact
A1: IMPACT
B2: 0 = Jamais | 1 = Parfois | 2 = Souvent | 3 = Très souvent | C2: Evaluation 1 | D2: Evaluation 2
A3: Item | B3: Énoncé | C3: Valeur (0–3) | D3: Valeur (0-3)
A4: D28 | B4: Les difficultés ont un impact sur les résultats scolaires.
A5: D29 | B5: Elles affectent la relation avec les enseignants.
A6: D30 | B6: Elles génèrent du stress, une démotivation ou une baisse d’estime de soi.
B8: Total catégorie | C8: =SUM(C4:C6) -> 0 | D8: =SUM(D4:D6) -> 0

Sheet Synthèse
A1: Synthèse des scores
A3: Nom de l’élève | G3: Évaluateur
A4: Classe | G4: Date | H4: Evaluation 1 : Evaluation 2 :
B6: Evaluation 1 | E6: Evaluation 2
A7: Catégorie | B7: Total | C7: Max | D7: Pourcentage | E7: Total | F7: Max | G7: Pourcentage
A8: Inattention | B8: =A_Inattention!C16 -> 0 | C8: 30 | D8: =IFERROR(ROUND(B8/30,2),"") -> 0 | E8: =A_Inattention!D16 -> 0 | F8: 30 | G8: =IFERROR(ROUND(E8/30,2),"") -> 0
A9: Hyper/Impulsivité | B9: =B_HyperImpuls!C13 -> 0 | C9: 24 | D9: =IFERROR(ROUND(B9/24,2),"") -> 0 | E9: =B_HyperImpuls!D13 -> 0 | F9: 24 | G9: =IFERROR(ROUND(E9/24,2),"") -> 0
A10: Impact | B10: =E_Impact!C8 -> 0 | C10: 9 | D10: =IFERROR(ROUND(B10/9,2),"") -> 0 | E10: =E_Impact!D8 -> 0 | F10: 9 | G10: =IFERROR(ROUND(E10/9,2),"") -> 0
B12: Evaluation 1 | E12: Evaluation 2
A13: Sous-scores (fonctions exécutives et réactions) | D13: Pourcentage | G13: Pourcentage
A14: Activation | B14: =A_Inattention!C10+A_Inattention!C14+C_Devoirs!C4+C_Devoirs!C11 -> 0 | C14: 12 | D14: =IFERROR(ROUND(B14/12,2),"") -> 0 | E14: =A_Inattention!D10+A_Inattention!D14+C_Devoirs!D4+C_Devoirs!D11 -> 0 | F14: 12 | G14: =IFERROR(ROUND(E14/12,2),"") -> 0
A15: Organisation | B15: =A_Inattention!C9+A_Inattention!C11+A_Inattention!C13+C_Devoirs!C10+C_Devoirs!C8 -> 0 | C15: 15 | D15: =IFERROR(ROUND(B15/15,2),"") -> 0 | E15: =A_Inattention!D9+A_Inattention!D11+A_Inattention!D13+C_Devoirs!D10+C_Devoirs!D8 -> 0 | F15: 15 | G15: =IFERROR(ROUND(E15/15,2),"") -> 0
A16: Devoirs | B16: =C_Devoirs!C14 -> 0 | C16: 27 | D16: =IFERROR(ROUND(B16/27,2),"") -> 0 | E16: =C_Devoirs!D14 -> 0 | F16: 27 | G16: =IFERROR(ROUND(E16/27,2),"") -> 0
A17: Réactions de confrontation | B17: =D_Réactions_confrontation!C15 -> 0 | C17: 30 | D17: =IFERROR(ROUND(B17/30,2),"") -> 0 | E17: =D_Réactions_confrontation!D15 -> 0 | F17: 30 | G17: =IFERROR(ROUND(E17/30,2),"") -> 0
A19: Dimension | B19: Evaluation 1 | C19: Evaluation 2
A20: Inattention | B20: =D8 -> 0 | C20: =G8 -> 0
A21: Hyper/Impulsivité | B21: =D9 -> 0 | C21: =G9 -> 0
A22: Devoirs | B22: =D16 -> 0 | C22: =G16 -> 0
A23: Impact | B23: =D10 -> 0 | C23: =G10 -> 0
A24: Activation | B24: =D14 -> 0 | C24: =G14 -> 0
A25: Organisation | B25: =D15 -> 0 | C25: =G15 -> 0
A26: Réactions de confrontation | B26: =D17 -> 0 | C26: =G17 -> 0

Sheet Interprétation
A1: Interprétation – outil de repérage (usage éducatif, non diagnostique)
A3: Seuils indicatifs (à adapter selon le contexte)
A4: Dimension | B4: Faible | C4: Modéré | D4: Élevé | E4: Actions pédagogiques prioritaires
A5: Inattention (0–30) | B5: 0–9 | C5: 10–17 | D5: ≥18 | E5: Activation, fractionnement, guidage du démarrage, aides visuelles
A6: Hyper/Impulsivité (0–24) | B6: 0–7 | C6: 8–13 | D6: ≥14 | E6: Pauses motrices, contrat de classe, prévention, canaliser l’énergie
A7: Devoirs (0–27) | B7: 0–8 | C7: 9–15 | D7: ≥16 | E7: Ritualiser, alléger, structurer, planifier, feedback court
A8: Impact (0–9) | B8: 0–2 | C8: 3–5 | D8: ≥6 | E8: Coordination école–famille–réseau, soutien émotionnel
A9: Activation (0–12) | B9: 0–3 | C9: 4–7 | D9: ≥8 | E9: Micro-objectifs, minuteur, démarrage guidé, renforcement
A10: Organisation (0–15) | B10: 0–4 | C10: 5–9 | D10: ≥10 | E10: Checklists, routines, organisation matériel, agenda
A11: Réactions confrontation (0-30) | B11: 0-9 | C11: 10-19 | D11: ≥20 | E11: Voir Checklist dans feuille "Intervention"
A13: Lecture transversale
A14: • A et/ou B élevés + D élevé : repérage fort → adaptations immédiates + discussion réseau.
A15: • C élevé isolé : difficulté d’autonomie / organisation / contexte familial → plan devoirs.
A16: • D : Score faible : réactions ponctuelles, souvent liées au contexte ou à la fatigue. / Score modéré : réactions fréquentes nécessitant des ajustements pédagogiques et relationnels. / Score élevé : difficultés marquées d’autorégulation dans les situations de contrainte.
A17: • Toujours rechercher : difficultés d’apprentissage, anxiété, sommeil, stress, dynamique relationnelle.

Sheet Ressources de l'élève
A1: Ressources et capacités de régulation de l’élève
A3: Cette feuille vise à identifier les ressources, compétences et capacités de régulation émotionnelle, comportementale et cognitive de l’élève afin de soutenir l’intervention. La présence d’une ressource, même partielle ou contextuelle, constitue un levier d’évolution.
A4: Domaine | B4: Capacité / ressource observée | C4: Présence (0–3) | D4: Commentaires / exemples
A5: Régulation émotionnelle | B5: Peut retrouver le calme après un temps de pause ou avec aide.
A6: Régulation émotionnelle | B6: Peut se calmer après un délai (même long) sans escalader davantage.
A7: Régulation émotionnelle | B7: Accepte une pause proposée ou un changement de rythme.
A8: Régulation émotionnelle | B8: Identifie ses émotions ou signaux de débordement (même après coup).
A9: Régulation émotionnelle | B9: Peut utiliser un outil apaisant (respiration, objet, musique, coin calme) lorsqu’il/elle y est invité(e).
A10: Régulation émotionnelle | B10: Peut demander de l’aide ou un temps de pause avant de “déborder” (même rarement).
A11: Régulation comportementale | B11: Accepte une médiation adulte lors d’un conflit.
A12: Régulation comportementale | B12: Peut différer une réaction (attendre, respirer, se lever) avec aide.
A13: Régulation comportementale | B13: Parvient à reprendre une activité après désescalade.
A14: Régulation comportementale | B14: Parvient à réparer la relation après un conflit (excuses, reprise du lien) avec guidance.
A15: Régulation comportementale | B15: Suit une consigne après reformulation / clarification (2e essai).
A16: Métacognition | B16: Reconnaît après coup ce qui a déclenché la difficulté (tâche, fatigue, injustice perçue, bruit…).
... A36: Environnement / cadre | B36: Bénéficie d’un adulte “référent” ou d’un point d’ancrage relationnel.
A38: Autres ressources personnalisées (à compléter)

Sheet Intervention
A1: Document de synthèse-suivi-décisions-intervention
A3: Nom de l’élève | B3: =Synthèse!B3 -> 0
A4: Classe | B4: =Synthèse!B4 -> 0
A5: Date | B5: =Synthèse!H4 -> Evaluation 1 : Evaluation 2 :
A6: Participants (rôle)
A7: Contexte / forces / déclencheurs
A9: Scores | B9: Evaluation 1 | C9: Evaluation 2
A10: Inattention | B10: =Synthèse!D8 -> 0 | C10: =Synthèse!G8 -> 0 | J10: Outil de prévention et de régulation (non disciplinaire) 🧠 AVANT la tâche (prévenir) ☐ Consigne courte, claire, donnée une seule fois ☐ Tâche fractionnée (1 objectif à la fois) ☐ Quantité réduite (niveau inchangé) ☐ Choix cadré proposé (A ou B) ☐ Temps de travail limité et visible (minuteur) ▶️ DÉMARRAGE (clé) ☐ Démarrage guidé (1re étape faite avec l’adulte) ☐ Vérification rapide de la compréhension ☐ Objectif atteignable annoncé ☐ Valorisation de l’entrée dans la tâche (pas du résultat) ⚠️ SIGNAUX D’ALERTE (intervenir tôt) ☐ Agitation / négociation / évitement repérés ☐ Pause anticipée proposée (sans justification) ☐ Voix calme, posture basse ☐ Interaction discrète (pas publique) 🔥 EN CAS DE MONTÉE ☐ Sortie de la tâche avant l’explosion ☐ Pas de rapport de force ☐ Pas de sanction à chaud ☐ L’adulte co-régule (prête son calme) 🧩 APRÈS (réparer) ☐ Retour au calme avant toute exigence ☐ Réparation guidée (faits, pas intention) ☐ Reprise partielle de la tâche si possible ☐ Valorisation du retour au calme / de l’effort 🚫 À ÉVITER (toujours) ☐ Ironie / défi / bras de fer ☐ Multiplication des rappels verbaux ☐ Punition immédiate ☐ Moralisation
A11: Hyper/Impulsivité | B11: =Synthèse!D9 -> 0 | C11: =Synthèse!G9 -> 0
A12: Devoirs | B12: =Synthèse!D16 -> 0 | C12: =Synthèse!G16 -> 0
A13: Impact | B13: =Synthèse!D10 -> 0 | C13: =Synthèse!G10 -> 0 | F13: Stratégies relationnelles
A14: Activation | B14: =Synthèse!D14 -> 0 | C14: =Synthèse!G14 -> 0
A15: Organisation | B15: =Synthèse!D15 -> 0 | C15: =Synthèse!G15 -> 0
A16: Réactions de confrontation | B16: =Synthèse!D17 -> 0 | C16: =Synthèse!G17 -> 0
A18: Hypothèses / besoins prioritaires | F18: Responsables & échéance
A22: Aménagements décidés en classe | F22: Indicateurs de progrès (observables)
A28: Références : DSM-5-TR (APA, 2022) ; Conners 3 ; Barkley (fonctions exécutives) ; Gaudreau & Nadeau (fonctionnement scolaire)
